annotrack/__init__.py
annotrack/_dock_widgets.py
annotrack/annotation.py
annotrack/misc.py
annotrack/napari.yaml
annotrack/sample_from_meta.py
annotrack/sample_management.py
annotrack/sampling.py
annotrack/_tests/__init__.py
annotrack/_tests/test_sampling.py
annotrack-0.0.3.dist-info/LICENSE
annotrack-0.0.3.dist-info/METADATA
annotrack-0.0.3.dist-info/WHEEL
annotrack-0.0.3.dist-info/entry_points.txt
annotrack-0.0.3.dist-info/top_level.txt
annotrack-0.0.3.dist-info/RECORD
