Metadata-Version: 2.1
Name: annotrack
Version: 0.0.3
Summary: napari plugin for annotating tracks to estimate error rates
Home-page: https://github.com/abigailmcgovern/annotrack
Author: Abigail S McGovern
Author-email: abigail_mcgovern@hotmail.com
License: BSD-3-Clause
Project-URL: Bug Tracker, https://github.com/abigailmcgovern/annotrack/issues
Project-URL: Documentation, https://github.com/abigailmcgovern/annotrack#README.md
Project-URL: Source Code, https://github.com/abigailmcgovern/annotrack
Project-URL: User Support, https://github.com/abigailmcgovern/annotrack/issues
Classifier: Programming Language :: Python :: 3
Classifier: License :: OSI Approved :: BSD License
Classifier: Operating System :: OS Independent
Classifier: Intended Audience :: Science/Research
Classifier: Topic :: Scientific/Engineering
Classifier: Topic :: Scientific/Engineering :: Image Processing
Classifier: Framework :: napari
Requires-Python: >=3.7
License-File: LICENSE
Requires-Dist: dask
Requires-Dist: napari
Requires-Dist: numpy
Requires-Dist: zarr
Requires-Dist: pandas
Provides-Extra: docs
Requires-Dist: sphinx ; extra == 'docs'
Provides-Extra: io
Requires-Dist: nd2 ; extra == 'io'
Provides-Extra: testing
Requires-Dist: pytest ; extra == 'testing'
